odoo/addons/mis_builder_total_committed_purchase/README.rst
odoo/addons/mis_builder_total_committed_purchase/__init__.py
odoo/addons/mis_builder_total_committed_purchase/__manifest__.py
odoo/addons/mis_builder_total_committed_purchase/data/mis_total_committed_purchase.sql
odoo/addons/mis_builder_total_committed_purchase/data/mis_total_committed_purchase_analytic_account_rel.sql
odoo/addons/mis_builder_total_committed_purchase/i18n/it.po
odoo/addons/mis_builder_total_committed_purchase/i18n/mis_builder_total_committed_purchase.pot
odoo/addons/mis_builder_total_committed_purchase/models/__init__.py
odoo/addons/mis_builder_total_committed_purchase/models/mis_total_committed_purchase.py
odoo/addons/mis_builder_total_committed_purchase/readme/CONTRIBUTORS.rst
odoo/addons/mis_builder_total_committed_purchase/readme/CREDITS.rst
odoo/addons/mis_builder_total_committed_purchase/readme/DESCRIPTION.rst
odoo/addons/mis_builder_total_committed_purchase/readme/HISTORY.rst
odoo/addons/mis_builder_total_committed_purchase/readme/ROADMAP.rst
odoo/addons/mis_builder_total_committed_purchase/readme/USAGE.rst
odoo/addons/mis_builder_total_committed_purchase/readme/newsfragments/.gitignore
odoo/addons/mis_builder_total_committed_purchase/security/mis_total_committed_purchase.xml
odoo/addons/mis_builder_total_committed_purchase/static/description/icon.png
odoo/addons/mis_builder_total_committed_purchase/static/description/index.html
odoo/addons/mis_builder_total_committed_purchase/views/mis_total_committed_purchase.xml
odoo_addon_mis_builder_total_committed_purchase-16.0.1.0.0.6.dist-info/METADATA
odoo_addon_mis_builder_total_committed_purchase-16.0.1.0.0.6.dist-info/WHEEL
odoo_addon_mis_builder_total_committed_purchase-16.0.1.0.0.6.dist-info/top_level.txt
odoo_addon_mis_builder_total_committed_purchase-16.0.1.0.0.6.dist-info/RECORD
