Metadata-Version: 2.1
Name: odoo-addon-mis_builder_total_committed_purchase
Version: 16.0.1.0.0.6
Summary: Addon to create a alternative source based on all purchase order line with MIS Builder.
Home-page: https://github.com/OCA/mis-builder-contrib
Author: ACSONE SA/NV, Camptocamp, Odoo Community Association (OCA)
Author-email: support@odoo-community.org
License: AGPL-3
Classifier: Programming Language :: Python
Classifier: Framework :: Odoo
Classifier: Framework :: Odoo :: 16.0
Classifier: License :: OSI Approved :: GNU Affero General Public License v3
Requires-Python: >=3.10
Requires-Dist: odoo-addon-mis-builder <16.1dev,>=16.0dev
Requires-Dist: odoo <16.1dev,>=16.0a
